[ { "domain":"draw.seeyue.top","subject":"","start": , "expire": , "issuer":"","status":"Expired","statuscolor":"error","check":"2024 05 05 01:06:28","remain":"0"},{"domain":"img.seeyue.top","subject":"CN=img.seeyue.top","start":"2024 03 02 00:00:00","expire":"2025 03 02 23:59:59","issuer":"C=CN; O=TrustAsia Technologies, Inc.; CN=TrustAsia RSA DV TLS CA G2","status":"Valid","statuscolor":"success","check":"2024 05 05 01:06:30","remain":"302"},{"domain":"matomo.seeyue.top","subject":"","start": , "expire": , "issuer":"","status":"Expired","statuscolor":"error","check":"2024 05 05 01:06:30","remain":"0"},{"domain":"nav.seeyue.top","subject":"","start": , "expire": , "issuer":"","status":"Expired","statuscolor":"error","check":"2024 05 05 01:06:31","remain":"0"},{"domain":"pan.seeyue.top","subject":"","start": , "expire": , "issuer":"","status":"Expired","statuscolor":"error","check":"2024 05 05 01:06:31","remain":"0"},{"domain":"pic.seeyue.top","subject":"","start": , "expire": , "issuer":"","status":"Expired","statuscolor":"error","check":"2024 05 05 01:06:32","remain":"0"},{"domain":"state.seeyue.top","subject":"","start": , "expire": , "issuer":"","status":"Expired","statuscolor":"error","check":"2024 05 05 01:06:32","remain":"0"},{"domain":"uptime.seeyue.top","subject":"","start": , "expire": , "issuer":"","status":"Expired","statuscolor":"error","check":"2024 05 05 01:06:33","remain":"0"},{"domain":"umami.seeyue.top","subject":"","start": , "expire": , "issuer":"","status":"Expired","statuscolor":"error","check":"2024 05 05 01:06:33","remain":"0"},{"domain":"ward.seeyue.top","subject":"","start": , "expire": , "issuer":"","status":"Expired","statuscolor":"error","check":"2024 05 05 01:06:33","remain":"0" } ]
